fourieroptics/__init__.py
fourieroptics/apertures.py
fourieroptics/helpers.py
fourieroptics/propagators.py
fourieroptics-0.0.5.dist-info/LICENSE
fourieroptics-0.0.5.dist-info/METADATA
fourieroptics-0.0.5.dist-info/WHEEL
fourieroptics-0.0.5.dist-info/top_level.txt
fourieroptics-0.0.5.dist-info/RECORD
