Metadata-Version: 2.1
Name: fourieroptics
Version: 0.0.5
Summary: Library for Fourier Optics Helper Functions
Home-page: UNKNOWN
Author: Bretton Scarbrough
Author-email: <bretton.scarbrough@gmail.com>
License: UNKNOWN
Keywords: python,fourier,optics,fourier optics
Platform: UNKNOWN
Classifier: Development Status :: 1 - Planning
Classifier: Intended Audience :: Developers
Classifier: Programming Language :: Python :: 3
Classifier: Operating System :: Unix
Classifier: Operating System :: MacOS :: MacOS X
Classifier: Operating System :: Microsoft :: Windows
License-File: LICENSE
Requires-Dist: numpy>=2.0.0
Requires-Dist: scipy
